gamdl/__init__.py
gamdl/__main__.py
gamdl/utils.py
gamdl/api/__init__.py
gamdl/api/apple_music_api.py
gamdl/api/constants.py
gamdl/api/itunes_api.py
gamdl/cli/__init__.py
gamdl/cli/cli.py
gamdl/cli/cli_config.py
gamdl/cli/config_file.py
gamdl/cli/constants.py
gamdl/cli/utils.py
gamdl/downloader/__init__.py
gamdl/downloader/constants.py
gamdl/downloader/downloader.py
gamdl/downloader/downloader_base.py
gamdl/downloader/downloader_music_video.py
gamdl/downloader/downloader_song.py
gamdl/downloader/downloader_uploaded_video.py
gamdl/downloader/enums.py
gamdl/downloader/exceptions.py
gamdl/downloader/hardcoded_wvd.py
gamdl/downloader/types.py
gamdl/interface/__init__.py
gamdl/interface/constants.py
gamdl/interface/enums.py
gamdl/interface/interface.py
gamdl/interface/interface_music_video.py
gamdl/interface/interface_song.py
gamdl/interface/interface_uploaded_video.py
gamdl/interface/types.py
gamdl-2.8.4.dist-info/licenses/LICENSE
gamdl-2.8.4.dist-info/METADATA
gamdl-2.8.4.dist-info/WHEEL
gamdl-2.8.4.dist-info/entry_points.txt
gamdl-2.8.4.dist-info/top_level.txt
gamdl-2.8.4.dist-info/RECORD
