Metadata-Version: 2.4
Name: gamdl
Version: 2.8.4
Summary: A command-line app for downloading Apple Music songs, music videos and post videos.
License-Expression: MIT
Project-URL: Repository, https://github.com/glomatico/gamdl
Requires-Python: >=3.10
License-File: LICENSE
Requires-Dist: async-lru>=2.0.5
Requires-Dist: click>=8.3.0
Requires-Dist: colorama>=0.4.6
Requires-Dist: dataclass-click>=1.0.4
Requires-Dist: httpx>=0.28.1
Requires-Dist: inquirerpy>=0.3.4
Requires-Dist: m3u8>=6.0.0
Requires-Dist: mutagen>=1.47.0
Requires-Dist: pillow>=12.0.0
Requires-Dist: pywidevine>=1.8.0
Requires-Dist: yt-dlp>=2025.10.22
Dynamic: license-file
